sqlblock/__init__.py
sqlblock/setup.py
sqlblock/sqltext.py
sqlblock/old/__init__.py
sqlblock/old/cursor.py
sqlblock/old/decorator.py
sqlblock/old/postgres.py
sqlblock/postgres/__init__.py
sqlblock/postgres/_sqlblock.py
sqlblock/postgres/connection.py
sqlblock/utils/__init__.py
sqlblock/utils/json.py
sqlblock-0.6.6.dist-info/LICENSE
sqlblock-0.6.6.dist-info/METADATA
sqlblock-0.6.6.dist-info/WHEEL
sqlblock-0.6.6.dist-info/top_level.txt
sqlblock-0.6.6.dist-info/RECORD
